konfuzio_sdk_extras_list.py
konfuzio_sdk/__init__.py
konfuzio_sdk/api.py
konfuzio_sdk/cli.py
konfuzio_sdk/data.py
konfuzio_sdk/evaluate.py
konfuzio_sdk/extras.py
konfuzio_sdk/normalize.py
konfuzio_sdk/regex.py
konfuzio_sdk/samples.py
konfuzio_sdk/schemas.py
konfuzio_sdk/settings_importer.py
konfuzio_sdk/urls.py
konfuzio_sdk/utils.py
konfuzio_sdk/bento/__init__.py
konfuzio_sdk/bento/base/__init__.py
konfuzio_sdk/bento/base/base_services.py
konfuzio_sdk/bento/base/utils.py
konfuzio_sdk/bento/categorization/__init__.py
konfuzio_sdk/bento/categorization/categorizationai_service.py
konfuzio_sdk/bento/categorization/schemas.py
konfuzio_sdk/bento/categorization/utils.py
konfuzio_sdk/bento/extraction/__init__.py
konfuzio_sdk/bento/extraction/rfextractionai_service.py
konfuzio_sdk/bento/extraction/rfextractionai_service_for_legacy_trainer.py
konfuzio_sdk/bento/extraction/schemas.py
konfuzio_sdk/bento/extraction/utils.py
konfuzio_sdk/bento/file_splitting/__init__.py
konfuzio_sdk/bento/file_splitting/schemas.py
konfuzio_sdk/bento/file_splitting/splittingai_service.py
konfuzio_sdk/bento/file_splitting/utils.py
konfuzio_sdk/tokenizer/__init__.py
konfuzio_sdk/tokenizer/base.py
konfuzio_sdk/tokenizer/paragraph_and_sentence.py
konfuzio_sdk/tokenizer/regex.py
konfuzio_sdk/trainer/__init__.py
konfuzio_sdk/trainer/base.py
konfuzio_sdk/trainer/document_categorization.py
konfuzio_sdk/trainer/file_splitting.py
konfuzio_sdk/trainer/image.py
konfuzio_sdk/trainer/information_extraction.py
konfuzio_sdk/trainer/tokenization.py
konfuzio_sdk/trainer/utils.py
konfuzio_sdk-0.3.46.dist-info/licenses/LICENSE.md
konfuzio_sdk-0.3.46.dist-info/METADATA
konfuzio_sdk-0.3.46.dist-info/WHEEL
konfuzio_sdk-0.3.46.dist-info/entry_points.txt
konfuzio_sdk-0.3.46.dist-info/top_level.txt
konfuzio_sdk-0.3.46.dist-info/RECORD
