Metadata-Version: 2.4
Name: konfuzio_sdk
Version: 0.3.46
Summary: Konfuzio Software Development Kit
Home-page: https://dev.konfuzio.com/sdk/index.html
Author: Helm & Nagel GmbH
Author-email: info@helm-nagel.com
Classifier: Programming Language :: Python :: 3
Classifier: Programming Language :: Python :: 3.11
Classifier: Programming Language :: Python :: 3.12
Classifier: Programming Language :: Python :: 3.13
Classifier: Operating System :: OS Independent
Requires-Python: >=3.11
License-File: LICENSE.md
Requires-Dist: bentoml>=1.4.13
Requires-Dist: fastapi>=0.115.12
Requires-Dist: certifi>=2025.4.26
Requires-Dist: cloudpickle>=3.1.1
Requires-Dist: filetype>=1.2.0
Requires-Dist: lz4>=4.4.4
Requires-Dist: matplotlib==3.10.7; python_version >= "3.13"
Requires-Dist: matplotlib>=3.10.0; python_version < "3.13"
Requires-Dist: nltk>=3.9.0
Requires-Dist: numpy<3,>=2.1.0
Requires-Dist: pandas>=2.0.0
Requires-Dist: Pillow>=11.2.1
Requires-Dist: pydantic>=2.11.4
Requires-Dist: python-dateutil>=2.9.0.post0
Requires-Dist: python-decouple>=3.8
Requires-Dist: python-dotenv>=1.1.0
Requires-Dist: requests>=2.32.3
Requires-Dist: regex>=2024.11.6
Requires-Dist: scikit-learn>=1.6.1
Requires-Dist: scipy>=1.15.0
Requires-Dist: setuptools
Requires-Dist: tabulate>=0.9.0
Requires-Dist: tqdm>=4.67.1
Requires-Dist: pympler>=1.1
Requires-Dist: openai>=1.102.0
Provides-Extra: dev
Requires-Dist: autodoc_pydantic>=2.2.0; extra == "dev"
Requires-Dist: coverage>=7.8.0; extra == "dev"
Requires-Dist: jupytext>=1.17.1; extra == "dev"
Requires-Dist: pytest>=8.3.5; extra == "dev"
Requires-Dist: pre-commit>=4.2.0; extra == "dev"
Requires-Dist: parameterized>=0.9.0; extra == "dev"
Requires-Dist: Sphinx>=7.0.0; extra == "dev"
Requires-Dist: sphinx-toolbox>=4.0.0; extra == "dev"
Requires-Dist: sphinx-reload>=0.2.0; extra == "dev"
Requires-Dist: sphinx-notfound-page>=1.1.0; extra == "dev"
Requires-Dist: m2r2>=0.3.4; extra == "dev"
Requires-Dist: nbval>=0.11.0; extra == "dev"
Requires-Dist: sphinx-sitemap>=2.6.0; extra == "dev"
Requires-Dist: sphinx-rtd-theme>=3.0.2; extra == "dev"
Requires-Dist: sphinxcontrib-jquery>=4.1; extra == "dev"
Requires-Dist: sphinxcontrib-mermaid>=1.0.0; extra == "dev"
Requires-Dist: sphinx-copybutton>=0.5.2; extra == "dev"
Requires-Dist: myst_nb>=1.2.0; extra == "dev"
Requires-Dist: ruff>=0.11.10; extra == "dev"
Requires-Dist: pytest-rerunfailures>=15.1; extra == "dev"
Provides-Extra: ai
Requires-Dist: keras==3.10.0; python_version >= "3.13" and extra == "ai"
Requires-Dist: tf-keras>=2.16.0; extra == "ai"
Requires-Dist: chardet>=5.2.0; extra == "ai"
Requires-Dist: accelerate>=1.7.0; extra == "ai"
Requires-Dist: datasets==3.6.0; python_version >= "3.13" and extra == "ai"
Requires-Dist: evaluate==0.4.3; python_version >= "3.13" and extra == "ai"
Requires-Dist: mlflow>=2.22.0; extra == "ai"
Requires-Dist: ml-dtypes==0.5.1; python_version >= "3.13" and extra == "ai"
Requires-Dist: datasets>=3.6.0; python_version < "3.13" and extra == "ai"
Requires-Dist: timm>=1.0.15; extra == "ai"
Requires-Dist: tensorflow-cpu<2.20.0,>=2.16.0; python_version < "3.13" and extra == "ai"
Requires-Dist: h5py==3.15.0; python_version >= "3.13" and extra == "ai"
Requires-Dist: torchvision>=0.22.0; extra == "ai"
Requires-Dist: torch>=2.7.0; extra == "ai"
Requires-Dist: tensorflow-cpu==2.20.0; python_version >= "3.13" and extra == "ai"
Requires-Dist: transformers>=4.51.3; extra == "ai"
Requires-Dist: evaluate>=0.4.3; python_version < "3.13" and extra == "ai"
Dynamic: author
Dynamic: author-email
Dynamic: classifier
Dynamic: description
Dynamic: description-content-type
Dynamic: home-page
Dynamic: license-file
Dynamic: provides-extra
Dynamic: requires-dist
Dynamic: requires-python
Dynamic: summary
